pyrcs/__init__.py
pyrcs/_base.py
pyrcs/_updater.py
pyrcs/collector.py
pyrcs/converter.py
pyrcs/parser.py
pyrcs/utils.py
pyrcs/data/.metadata
pyrcs/data/location-names-errata-regex.json
pyrcs/data/location-names-errata.json
pyrcs/data/site-map.json
pyrcs/data/catalogue/crs-CRS0.json
pyrcs/data/catalogue/depots-depots0.json
pyrcs/data/catalogue/electrification-independent-lines.pkl
pyrcs/data/catalogue/electrification-mast_prefix0.json
pyrcs/data/catalogue/elrs-elr0.json
pyrcs/data/catalogue/features-habdwild.json
pyrcs/data/catalogue/line-data-menu.json
pyrcs/data/catalogue/line-line_names.json
pyrcs/data/catalogue/other-assets-menu.json
pyrcs/data/catalogue/pride-pride0.json
pyrcs/data/catalogue/signal-signal_boxes0.json
pyrcs/data/catalogue/stations-station0.json
pyrcs/data/catalogue/track-diagrams.pkl
pyrcs/data/catalogue/tunnels-tunnels0.json
pyrcs/data/catalogue/viaducts-viaducts0.json
pyrcs/data/introduction/bridges-bridges0.pkl
pyrcs/data/line-data/bridges/bridges.json
pyrcs/data/line-data/crs-nlc-tiploc-stanox/notes.pkl
pyrcs/data/line-data/crs-nlc-tiploc-stanox/other-systems.pkl
pyrcs/data/line-data/crs-nlc-tiploc-stanox/a-z/a.pkl
pyrcs/data/line-data/crs-nlc-tiploc-stanox/a-z/b.pkl
pyrcs/data/line-data/crs-nlc-tiploc-stanox/a-z/c.pkl
pyrcs/data/line-data/crs-nlc-tiploc-stanox/a-z/d.pkl
pyrcs/data/line-data/crs-nlc-tiploc-stanox/a-z/e.pkl
pyrcs/data/line-data/crs-nlc-tiploc-stanox/a-z/f.pkl
pyrcs/data/line-data/crs-nlc-tiploc-stanox/a-z/g.pkl
pyrcs/data/line-data/crs-nlc-tiploc-stanox/a-z/h.pkl
pyrcs/data/line-data/crs-nlc-tiploc-stanox/a-z/i.pkl
pyrcs/data/line-data/crs-nlc-tiploc-stanox/a-z/j.pkl
pyrcs/data/line-data/crs-nlc-tiploc-stanox/a-z/k.pkl
pyrcs/data/line-data/crs-nlc-tiploc-stanox/a-z/l.pkl
pyrcs/data/line-data/crs-nlc-tiploc-stanox/a-z/m.pkl
pyrcs/data/line-data/crs-nlc-tiploc-stanox/a-z/n.pkl
pyrcs/data/line-data/crs-nlc-tiploc-stanox/a-z/o.pkl
pyrcs/data/line-data/crs-nlc-tiploc-stanox/a-z/p.pkl
pyrcs-1.0.4.dist-info/licenses/LICENSE
pyrcs-1.0.4.dist-info/METADATA
pyrcs-1.0.4.dist-info/WHEEL
pyrcs-1.0.4.dist-info/top_level.txt
pyrcs-1.0.4.dist-info/RECORD
