Metadata-Version: 2.4
Name: pyrcs
Version: 1.0.4
Summary: An open-source tool for collecting railway codes used in different UK rail industry systems
Home-page: https://github.com/mikeqfu/pyrcs
Author: Qian Fu
Author-email: q.fu@bham.ac.uk
License: MIT
Project-URL: Documentation, https://pyrcs.readthedocs.io/en/1.0.4/
Project-URL: Source, https://github.com/mikeqfu/pyrcs
Project-URL: Bug Tracker, https://github.com/mikeqfu/pyrcs/issues
Keywords: Python,Railway,Railway Codes,Bridges,Computer Reservation System,CRS,National Location Codes,NLC,Timing Point Locations,TIPLOC,Station Number Names,STANME,Station Numbers,STANOX,Electrification,Engineer's Line References,ELR,Mileage,Line Of Route,LOR,Railway Line Names,Railway Bridges,Stations,Signal Boxes,Tunnels,Viaducts,Depots,Tracks
Classifier: Intended Audience :: Developers
Classifier: Intended Audience :: Education
Classifier: Intended Audience :: Science/Research
Classifier: Topic :: Education
Classifier: Topic :: Scientific/Engineering
Classifier: Topic :: Software Development
Classifier: Topic :: Utilities
Classifier: Programming Language :: Python :: 3
Classifier: Operating System :: Microsoft :: Windows
Classifier: Operating System :: POSIX :: Linux
Requires-Python: >=3.12
License-File: LICENSE
Requires-Dist: pyhelpers>=2.3.2
Requires-Dist: beautifulsoup4
Dynamic: author
Dynamic: author-email
Dynamic: home-page
Dynamic: license
Dynamic: license-file
Dynamic: project-url
Dynamic: summary
